validatorPCTE/__init__.py
validatorPCTE/validatorPCTE.py
validatorPCTE-0.0.1.dist-info/LICENSE
validatorPCTE-0.0.1.dist-info/METADATA
validatorPCTE-0.0.1.dist-info/WHEEL
validatorPCTE-0.0.1.dist-info/top_level.txt
validatorPCTE-0.0.1.dist-info/RECORD
